pypreroms/__init__.py
pypreroms/exemple.py
pypreroms-0.0.1.data/data/my_data/data_file
pypreroms-0.0.1.dist-info/LICENSE.txt
pypreroms-0.0.1.dist-info/METADATA
pypreroms-0.0.1.dist-info/WHEEL
pypreroms-0.0.1.dist-info/entry_points.txt
pypreroms-0.0.1.dist-info/top_level.txt
pypreroms-0.0.1.dist-info/RECORD
