Metadata-Version: 2.1
Name: pypreroms
Version: 0.0.1
Home-page: https://github.com/pypa/sampleproject
Author: Gorka Solana Arteche
Author-email: Gorka Solana Arteche <gorsol@gmail.com>
License: Copyright (c) 2016 The Python Packaging Authority (PyPA)        
Project-URL: Homepage, https://github.com/gorsol/pypreroms
Project-URL: Bug Tracker, https://github.com/gorsol/pypreroms/issues
Keywords: sample,setuptools,development
Classifier: Programming Language :: Python :: 3
Classifier: License :: OSI Approved :: MIT License
Classifier: Operating System :: OS Independent
Requires-Python: >=3.7, <4
License-File: LICENSE.txt
Requires-Dist: peppercorn
Provides-Extra: dev
Requires-Dist: check-manifest ; extra == 'dev'
Provides-Extra: test
Requires-Dist: coverage ; extra == 'test'
